README.md
setup.py
medspacy_pna/__init__.py
medspacy_pna/_extensions.py
medspacy_pna/adjudication.py
medspacy_pna/constants.py
medspacy_pna/display.py
medspacy_pna/ehost_writer.py
medspacy_pna/util.py
medspacy_pna.egg-info/PKG-INFO
medspacy_pna.egg-info/SOURCES.txt
medspacy_pna.egg-info/dependency_links.txt
medspacy_pna.egg-info/requires.txt
medspacy_pna.egg-info/top_level.txt
medspacy_pna/document_classification/__init__.py
medspacy_pna/document_classification/discharge_document_classifier.py
medspacy_pna/document_classification/document_classifier.py
medspacy_pna/document_classification/emergency_document_classifier.py
medspacy_pna/document_classification/ml_document_classifier.py
medspacy_pna/document_classification/radiology_document_classifier.py
medspacy_pna/resources/__init__.py
medspacy_pna/resources/callbacks.py
medspacy_pna/resources/__pycache__/__init__.cpython-38.pyc
medspacy_pna/resources/clinical/__init__.py
medspacy_pna/resources/clinical/clinical_context_rules.json
medspacy_pna/resources/clinical/clinical_postprocess_rules.py
medspacy_pna/resources/clinical/clinical_section_rules.json
medspacy_pna/resources/clinical/__pycache__/__init__.cpython-38.pyc
medspacy_pna/resources/clinical/__pycache__/clinical_postprocess_rules.cpython-38.pyc
medspacy_pna/resources/common/__init__.py
medspacy_pna/resources/common/anatomy_concept_tag_rules.json
medspacy_pna/resources/common/anatomy_descriptor_modifier_rules.json
medspacy_pna/resources/common/common_postprocess_rules.py
medspacy_pna/resources/common/common_preprocess_rules.py
medspacy_pna/resources/common/concept_tag_rules.json
medspacy_pna/resources/common/context_rules.json
medspacy_pna/resources/common/target_rules.json
medspacy_pna/resources/common/__pycache__/__init__.cpython-38.pyc
medspacy_pna/resources/common/__pycache__/common_postprocess_rules.cpython-38.pyc
medspacy_pna/resources/common/__pycache__/common_preprocess_rules.cpython-38.pyc
medspacy_pna/resources/configs/__init__.py
medspacy_pna/resources/configs/discharge.json
medspacy_pna/resources/configs/emergency.json
medspacy_pna/resources/configs/radiology.json
medspacy_pna/resources/discharge/__init__.py
