Metadata-Version: 2.1
Name: medspacy-pna
Version: 0.0.0.3
Summary: Flexible medspaCy NLP pipeline for detecting assertions of pneumonia in different clinical notes.
Author: alec.chapman
Author-email: alec.chapman@hsc.utah.edu
License: UNKNOWN
Platform: UNKNOWN
